legacy_font_converter/__init__.py
legacy_font_converter/legacy_font_converter.py
legacy_font_converter/resources/sutonnymj.json
legacy_font_converter/special_trie.py
legacy_font_converter-0.1.3.dist-info/METADATA
legacy_font_converter-0.1.3.dist-info/WHEEL
legacy_font_converter-0.1.3.dist-info/RECORD
